voxcmd.py
voxcmd-0.1.0.dist-info/METADATA
voxcmd-0.1.0.dist-info/WHEEL
voxcmd-0.1.0.dist-info/entry_points.txt
voxcmd-0.1.0.dist-info/top_level.txt
voxcmd-0.1.0.dist-info/RECORD
