Metadata-Version: 2.4
Name: voxcmd
Version: 0.1.0
Requires-Dist: click
